ngstrefftz_avx2.libs/libngbla-2e2df476.so
ngstrefftz_avx2.libs/_pytents-b20a149f.so
ngstrefftz_avx2.libs/libngcomp-26daf60a.so
ngstrefftz_avx2.libs/libngfem-8021b580.so
ngstrefftz_avx2.libs/libngstd-793f6aef.so
ngstrefftz_avx2.libs/libsolve-b313dc32.so
ngstrefftz_avx2.libs/libngla-4dcf8323.so
ngstents/_pytents.so
ngstrefftz_avx2-0.2.0.dist-info/top_level.txt
ngstrefftz_avx2-0.2.0.dist-info/LICENSE
ngstrefftz_avx2-0.2.0.dist-info/METADATA
ngstrefftz_avx2-0.2.0.dist-info/RECORD
ngstrefftz_avx2-0.2.0.dist-info/WHEEL
ngstrefftz/_trefftz.so
ngstrefftz/__init__.py
