Metadata-Version: 2.1
Name: ngstrefftz-avx2
Version: 0.2.0
Summary: NGSTrefftz is an add-on to NGSolve for Trefftz methods.
Home-page: https://github.com/PaulSt/ngstrefftz
Author: Paul Stocker
Author-email: p.stocker@math.uni-goettingen.de
Requires-Python: >=3.5
License-File: LICENSE
Requires-Dist: ngsolve-avx2 (>=6.2.2204)
